{"session":{"id":"87202fbf-300a-44ed-b85b-9f584fb15245","name":"Sem 2 Week 4 COA122","start_time":"2026-02-26T15:00:00","end_time":"2026-02-26T17:00:00","duration_minutes":120.0,"students":null,"flagged":null,"module_filter":null},"bucket_minutes":6.0,"points":[{"t_end":"2026-02-26T15:06:00+00:00","cumulative_submissions":201,"cumulative_students":44,"mean_incorrectness":0.475,"struggle_buckets":[{"label":"On Track","count":0},{"label":"Minor Issues","count":0},{"label":"Struggling","count":1},{"label":"Needs Help","count":43}],"difficulty_buckets":[{"label":"Easy","count":1},{"label":"Medium","count":3},{"label":"Hard","count":10},{"label":"Very Hard","count":0}],"needs_help_ids":["td0781","uo0752","kp0102","ef0541","jx0171","up0301","lk0311","fa0501","ml0131","qf0132","ld0801","sl0531","ti0662","tt0012","qf0222","lo0112","em0501","tj0581","kq0351","ze0221","ak0272","kl0811","st0251","gc0041","ep0511","ec0811","ew0611","ga0662","ut0402","uq0283","xj0121","tu0911","po0821","ou0022","kp0701","qc0742","ul0781","ax0201","af0811","eu0931","pp0741","jy0232","lq0562"]},{"t_end":"2026-02-26T15:12:00+00:00","cumulative_submissions":502,"cumulative_students":55,"mean_incorrectness":0.463,"struggle_buckets":[{"label":"On Track","count":0},{"label":"Minor Issues","count":0},{"label":"Struggling","count":3},{"label":"Needs Help","count":52}],"difficulty_buckets":[{"label":"Easy","count":1},{"label":"Medium","count":5},{"label":"Hard","count":12},{"label":"Very Hard","count":0}],"needs_help_ids":["sl0531","uo0752","qf0132","po0411","kp0102","tu0911","ef0541","em0501","ld0801","td0781","ga0662","lk0311","xj0121","ut0402","ou0022","ep0511","ti0662","aw0751","st0251","ze0221","ml0131","fa0501","jx0171","up0301","qc0742","kp0701","ul0781","gc0041","fu0661","ed0311","ff0582","lo0112","jo0031","af0811","eu0931","jz0382","kl0811","ec0811","ak0272","uu0571","yt0141","po0821","uq0283","jo0841","kq0351","ax0201","ji0861","tj0581","jy0232","qf0222","ew0271","ew0611"]},{"t_end":"2026-02-26T15:18:00+00:00","cumulative_submissions":865,"cumulative_students":63,"mean_incorrectness":0.471,"struggle_buckets":[{"label":"On Track","count":0},{"label":"Minor Issues","count":0},{"label":"Struggling","count":2},{"label":"Needs Help","count":61}],"difficulty_buckets":[{"label":"Easy","count":1},{"label":"Medium","count":5},{"label":"Hard","count":23},{"label":"Very Hard","count":1}],"needs_help_ids":["sl0531","uo0752","fa0501","kp0102","jx0171","ml0131","ef0541","em0501","ec0811","ul0781","ou0022","fu0661","tu0911","aw0751","qf0132","gc0041","xj0121","eu0931","yt0742","lk0311","kp0701","ak0272","ga0662","tj0581","uu0571","ld0801","zo0262","lo0112","ut0402","pp0741","ep0511","ti0662","ze0221","ax0201","po0411","ff0582","qc0742","up0301","ji0861","kq0351","jz0382","qf0222","ed0311","td0591","uu0141","sa0591","jo0841","yt0141","uq0283","tx0522","po0821","ul0491","xj0851","ew0611","af0811","kl0811","td0781","jy0232","ew0271","st0251","jo0031"]},{"t_end":"2026-02-26T15:24:00+00:00","cumulative_submissions":1232,"cumulative_students":67,"mean_incorrectness":0.474,"struggle_buckets":[{"label":"On Track","count":0},{"label":"Minor Issues","count":0},{"label":"Struggling","count":1},{"label":"Needs Help","count":66}],"difficulty_buckets":[{"label":"Easy","count":2},{"label":"Medium","count":6},{"label":"Hard","count":23},{"label":"Very Hard","count":1}],"needs_help_ids":["sl0531","uo0752","fa0501","lk0311","jx0171","ze0221","pp0741","ml0131","ut0402","ji0861","ld0801","ep0511","em0501","kp0102","yt0742","ou0022","ef0541","ec0811","up0301","gc0041","tj0581","aw0751","ul0781","fu0661","uu0571","eu0931","lo0112","kl0811","ew0611","td0591","ak0272","af0811","xj0121","tu0911","qf0132","td0781","ga0662","kp0701","tx0062","zo0262","po0411","jz0382","qc0742","ff0582","ew0271","kq0351","jo0031","ed0311","jo0841","tx0522","uq0283","yt0141","po0821","pz0611","so0511","qf0222","uu0141","ul0491","xj0851","ti0662","ax0201","jy0232","lq0562","fk0882","sa0591","st0251"]},{"t_end":"2026-02-26T15:30:00+00:00","cumulative_submissions":1576,"cumulative_students":70,"mean_incorrectness":0.478,"struggle_buckets":[{"label":"On Track","count":0},{"label":"Minor Issues","count":0},{"label":"Struggling","count":3},{"label":"Needs Help","count":67}],"difficulty_buckets":[{"label":"Easy","count":1},{"label":"Medium","count":4},{"label":"Hard","count":26},{"label":"Very Hard","count":1}],"needs_help_ids":["uo0752","sl0531","ga0662","tu0911","lk0311","em0501","ze0221","fa0501","ou0022","gc0041","jx0171","ml0131","ti0662","td0781","ji0861","yt0742","ut0402","fu0661","tj0581","ul0781","ec0811","jy0232","lo0112","kl0811","aw0751","ld0801","ep0511","eu0931","up0301","kp0102","po0821","ef0541","pp0741","xj0121","tx0522","ew0611","af0811","uu0571","jo0031","jz0382","ew0271","zo0262","td0591","qc0742","ak0272","qf0132","sa0591","kp0701","tx0062","xj0851","kq0351","jo0841","mi0621","ld0231","so0511","yt0141","ff0582","zz0603","ed0311","uu0141","pz0611","ul0491","po0411","qf0222","ax0201","uq0283","lq0562"]},{"t_end":"2026-02-26T15:36:00+00:00","cumulative_submissions":1913,"cumulative_students":74,"mean_incorrectness":0.48,"struggle_buckets":[{"label":"On Track","count":0},{"label":"Minor Issues","count":0},{"label":"Struggling","count":3},{"label":"Needs Help","count":71}],"difficulty_buckets":[{"label":"Easy","count":1},{"label":"Medium","count":4},{"label":"Hard","count":26},{"label":"Very Hard","count":1}],"needs_help_ids":["uo0752","sl0531","ga0662","ak0272","qf0132","ep0511","fa0501","lk0311","ze0221","ec0811","ml0131","tu0911","em0501","yt0742","fu0661","ut0402","ou0022","jo0031","gc0041","td0781","aw0751","jx0171","ul0781","ji0861","uu0571","lo0112","ti0662","kq0351","up0301","kl0811","jz0382","tj0581","jy0232","ld0801","eu0931","po0821","ew0271","kp0102","tx0522","tx0062","zo0262","ef0541","uu0141","ax0201","xj0121","ff0582","uq0283","ew0611","pp0741","qc0742","zz0603","af0811","kp0701","yt0141","sa0591","wa0871","jo0841","fj0482","fl0561","so0511","ed0311","jz0761","ld0231","mi0621","pz0611","ul0491","td0591","lq0562","po0411","qf0222","xj0851"]},{"t_end":"2026-02-26T15:42:00+00:00","cumulative_submissions":2252,"cumulative_students":74,"mean_incorrectness":0.48,"struggle_buckets":[{"label":"On Track","count":0},{"label":"Minor Issues","count":0},{"label":"Struggling","count":1},{"label":"Needs Help","count":73}],"difficulty_buckets":[{"label":"Easy","count":1},{"label":"Medium","count":4},{"label":"Hard","count":26},{"label":"Very Hard","count":1}],"needs_help_ids":["uo0752","ga0662","sl0531","tx0062","jo0031","ml0131","fa0501","td0781","lk0311","jx0171","ze0221","tu0911","ak0272","ep0511","qf0132","td0591","ou0022","yt0742","uu0141","ji0861","ec0811","em0501","zo0262","ut0402","jy0232","up0301","fu0661","ul0781","gc0041","aw0751","uq0283","uu0571","sa0591","lo0112","kq0351","ti0662","kl0811","mi0621","tx0522","ld0801","ew0271","jz0382","eu0931","fj0482","tj0581","po0821","ld0231","kp0102","lq0562","ef0541","qc0742","xj0121","ff0582","so0511","ew0611","pp0741","af0811","pz0611","yt0141","fl0561","jo0841","kp0701","ed0311","st0251","po0411","qf0222","ax0201","ul0491","wa0871","zz0603","fk0882","xj0851","jz0761"]},{"t_end":"2026-02-26T15:48:00+00:00","cumulative_submissions":2590,"cumulative_students":75,"mean_incorrectness":0.483,"struggle_buckets":[{"label":"On Track","count":0},{"label":"Minor Issues","count":1},{"label":"Struggling","count":1},{"label":"Needs Help","count":73}],"difficulty_buckets":[{"label":"Easy","count":2},{"label":"Medium","count":6},{"label":"Hard","count":23},{"label":"Very Hard","count":1}],"needs_help_ids":["jo0841","sl0531","uo0752","lk0311","qf0132","ga0662","fa0501","jo0031","xj0851","qf0222","tu0911","tx0062","td0781","ec0811","kp0701","aw0751","ml0131","td0591","gc0041","zo0262","ou0022","ze0221","uu0141","jx0171","ut0402","po0821","sa0591","ak0272","up0301","jy0232","ep0511","yt0742","ew0271","lo0112","ul0781","em0501","uu0571","fu0661","kq0351","ff0582","tx0522","ti0662","kl0811","lq0562","fj0482","mi0621","eu0931","tj0581","ld0801","ld0231","jz0382","qc0742","pp0741","kp0102","ew0611","ef0541","so0511","af0811","xj0121","fl0561","fpgb","st0251","yt0141","pz0611","uq0283","wa0871","ed0311","fk0882","po0411","ji0861","ul0491","ax0201","zz0603"]},{"t_end":"2026-02-26T15:54:00+00:00","cumulative_submissions":2901,"cumulative_students":77,"mean_incorrectness":0.48,"struggle_buckets":[{"label":"On Track","count":0},{"label":"Minor Issues","count":1},{"label":"Struggling","count":2},{"label":"Needs Help","count":74}],"difficulty_buckets":[{"label":"Easy","count":3},{"label":"Medium","count":4},{"label":"Hard","count":24},{"label":"Very Hard","count":1}],"needs_help_ids":["jo0841","qf0132","sl0531","uo0752","tu0911","kp0701","xj0851","ga0662","tx0062","fa0501","jo0031","ut0402","ou0022","yt0742","qf0222","ji0861","td0781","ec0811","xj0121","kq0351","sa0591","aw0751","td0591","gc0041","ml0131","zo0262","lo0112","ze0221","jx0171","jy0232","ak0272","po0821","up0301","tx0522","ew0271","yt0141","em0501","ul0781","uu0571","fu0661","ff0582","ti0662","fj0482","st0251","mi0621","ax0201","kl0811","ld0231","lq0562","eu0931","tj0581","ld0801","pp0741","jz0382","kp0102","qc0742","ef0541","ew0611","lk0311","so0511","af0811","fl0561","fpgb","xw0761","uq0283","pz0611","wa0871","ed0311","po0411","wo0851","ul0491","uu0141","ep0511","zz0603"]},{"t_end":"2026-02-26T16:00:00+00:00","cumulative_submissions":3043,"cumulative_students":77,"mean_incorrectness":0.48,"struggle_buckets":[{"label":"On Track","count":0},{"label":"Minor Issues","count":1},{"label":"Struggling","count":2},{"label":"Needs Help","count":74}],"difficulty_buckets":[{"label":"Easy","count":1},{"label":"Medium","count":5},{"label":"Hard","count":26},{"label":"Very Hard","count":0}],"needs_help_ids":["jo0841","qf0132","lk0311","sl0531","uo0752","kq0351","tu0911","kp0701","ga0662","tx0062","jy0232","ep0511","ak0272","fa0501","jo0031","ul0781","ut0402","ou0022","yt0742","qf0222","ji0861","xj0121","ec0811","td0781","sa0591","aw0751","gc0041","ml0131","zo0262","ze0221","lo0112","jx0171","po0821","up0301","tx0522","ew0271","xj0851","yt0141","em0501","uu0571","fu0661","ld0231","ff0582","fj0482","ti0662","mi0621","st0251","kl0811","td0591","ax0201","eu0931","ld0801","tj0581","lq0562","kp0102","jz0382","pp0741","qc0742","ef0541","ew0611","so0511","fl0561","fpgb","xw0761","af0811","pz0611","ul0491","ed0311","uq0283","po0411","wa0871","uu0141","zz0603","wo0851"]},{"t_end":"2026-02-26T16:06:00+00:00","cumulative_submissions":3110,"cumulative_students":80,"mean_incorrectness":0.48,"struggle_buckets":[{"label":"On Track","count":0},{"label":"Minor Issues","count":1},{"label":"Struggling","count":2},{"label":"Needs Help","count":77}],"difficulty_buckets":[{"label":"Easy","count":1},{"label":"Medium","count":5},{"label":"Hard","count":26},{"label":"Very Hard","count":0}],"needs_help_ids":["jo0841","qf0132","lk0311","sl0531","uo0752","kq0351","tu0911","kp0701","ga0662","tx0062","jy0232","ak0272","ep0511","fa0501","jo0031","ul0781","ut0402","ou0022","yt0742","qf0222","ec0811","xj0121","ji0861","td0781","sa0591","aw0751","ld0231","gc0041","ml0131","ze0221","zo0262","lo0112","jx0171","po0821","tx0522","up0301","td0591","ew0271","yt0141","em0501","xj0851","uu0571","fu0661","ff0582","fj0482","ti0662","mi0621","kl0811","st0251","ax0201","fpgb","wa0871","eu0931","ld0801","tj0581","lq0562","kp0102","jz0382","pp0741","ef0541","qc0742","sa0431","so0511","ew0611","fl0561","xw0761","td0063","ul0491","af0811","pz0611","ed0311","uq0283","mq0322","po0411","wo0851","uu0141","zz0603"]},{"t_end":"2026-02-26T16:12:00+00:00","cumulative_submissions":3160,"cumulative_students":81,"mean_incorrectness":0.48,"struggle_buckets":[{"label":"On Track","count":0},{"label":"Minor Issues","count":1},{"label":"Struggling","count":2},{"label":"Needs Help","count":78}],"difficulty_buckets":[{"label":"Easy","count":1},{"label":"Medium","count":4},{"label":"Hard","count":27},{"label":"Very Hard","count":0}],"needs_help_ids":["jo0841","qf0132","lk0311","sl0531","uo0752","kq0351","tu0911","kp0701","ga0662","tx0062","jy0232","ak0272","ep0511","fa0501","ld0231","jo0031","ul0781","ut0402","ou0022","yt0742","qf0222","ec0811","xj0121","ji0861","td0781","sa0591","aw0751","gc0041","ml0131","ze0221","zo0262","lo0112","jx0171","po0821","tx0522","up0301","td0591","ew0271","yt0141","em0501","xj0851","uu0571","fu0661","ff0582","fj0482","wo0851","ti0662","mi0621","kl0811","st0251","ax0201","fpgb","wa0871","eu0931","ld0801","tj0581","lq0562","kp0102","jz0382","pp0741","ef0541","qc0742","so0511","ew0611","fl0561","td0063","xw0761","ul0491","mm0521","af0811","sa0431","mq0322","pz0611","ed0311","uq0283","po0411","uu0141","zz0603"]},{"t_end":"2026-02-26T16:18:00+00:00","cumulative_submissions":3188,"cumulative_students":81,"mean_incorrectness":0.48,"struggle_buckets":[{"label":"On Track","count":0},{"label":"Minor Issues","count":1},{"label":"Struggling","count":2},{"label":"Needs Help","count":78}],"difficulty_buckets":[{"label":"Easy","count":1},{"label":"Medium","count":4},{"label":"Hard","count":27},{"label":"Very Hard","count":0}],"needs_help_ids":["jo0841","qf0132","lk0311","sl0531","uo0752","kq0351","tu0911","kp0701","ga0662","td0591","tx0062","jy0232","jo0031","ak0272","fa0501","ld0231","ep0511","yt0742","ul0781","ut0402","ou0022","qf0222","ji0861","td0781","xj0121","ec0811","sa0591","aw0751","gc0041","zo0262","ze0221","ml0131","lo0112","jx0171","po0821","tx0522","up0301","ew0271","em0501","yt0141","xj0851","fu0661","uu0571","fj0482","wo0851","fpgb","ti0662","ff0582","mi0621","sa0431","kl0811","st0251","eu0931","wa0871","ld0801","tj0581","ax0201","lq0562","kp0102","jz0382","pp0741","ef0541","so0511","ew0611","fl0561","xw0761","qc0742","mq0322","ul0491","af0811","pz0611","mm0521","td0063","ed0311","uq0283","po0411","uu0141","zz0603"]},{"t_end":"2026-02-26T16:24:00+00:00","cumulative_submissions":3271,"cumulative_students":83,"mean_incorrectness":0.481,"struggle_buckets":[{"label":"On Track","count":0},{"label":"Minor Issues","count":1},{"label":"Struggling","count":2},{"label":"Needs Help","count":80}],"difficulty_buckets":[{"label":"Easy","count":1},{"label":"Medium","count":4},{"label":"Hard","count":27},{"label":"Very Hard","count":0}],"needs_help_ids":["jo0841","qf0132","lk0311","td0591","sl0531","uo0752","kq0351","tu0911","kp0701","ga0662","tx0062","jy0232","jo0031","fa0501","ak0272","ld0231","ep0511","yt0742","ul0781","ut0402","qf0222","ou0022","ji0861","td0781","ec0811","xj0121","sa0591","aw0751","ze0221","zo0262","gc0041","ml0131","lo0112","jx0171","po0821","mm0521","tx0522","up0301","ew0271","em0501","yt0141","xj0851","fu0661","uu0571","fj0482","wo0851","fpgb","ti0662","ff0582","mi0621","kl0811","mq0322","eu0931","st0251","ld0801","td0063","wa0871","tj0581","ax0201","kp0102","id0821","lq0562","jz0382","pp0741","ef0541","so0511","fl0561","xw0761","ew0611","qc0742","kj0571","af0811","ul0491","pz0611","sa0431","ed0311","uq0283","po0411","uu0141","zz0603"]},{"t_end":"2026-02-26T16:30:00+00:00","cumulative_submissions":3304,"cumulative_students":86,"mean_incorrectness":0.481,"struggle_buckets":[{"label":"On Track","count":0},{"label":"Minor Issues","count":1},{"label":"Struggling","count":2},{"label":"Needs Help","count":83}],"difficulty_buckets":[{"label":"Easy","count":1},{"label":"Medium","count":4},{"label":"Hard","count":27},{"label":"Very Hard","count":0}],"needs_help_ids":["jo0841","qf0132","lk0311","td0591","sl0531","uo0752","kq0351","tu0911","kp0701","ga0662","tx0062","jy0232","jo0031","fa0501","ak0272","ld0231","ep0511","yt0742","ul0781","ut0402","qf0222","ou0022","ji0861","td0781","ec0811","xj0121","sa0591","aw0751","ze0221","zo0262","gc0041","ml0131","lo0112","jx0171","po0821","tx0522","mm0521","up0301","ew0271","em0501","sa0431","yt0141","xj0851","fu0661","uu0571","fj0482","wo0851","td0063","ti0662","fpgb","ff0582","mi0621","kl0811","mq0322","st0251","eu0931","ld0801","wa0871","tj0581","ax0201","id0821","kp0102","lq0562","jz0382","pp0741","ef0541","so0511","ew0611","qc0742","fj0472","jg0992","xw0761","xx0531","fl0561","af0811","ul0491","kj0571","pz0611","ed0311","uq0283","po0411","uu0141","zz0603"]},{"t_end":"2026-02-26T16:36:00+00:00","cumulative_submissions":3355,"cumulative_students":90,"mean_incorrectness":0.48,"struggle_buckets":[{"label":"On Track","count":0},{"label":"Minor Issues","count":1},{"label":"Struggling","count":2},{"label":"Needs Help","count":87}],"difficulty_buckets":[{"label":"Easy","count":1},{"label":"Medium","count":3},{"label":"Hard","count":28},{"label":"Very Hard","count":0}],"needs_help_ids":["jo0841","qf0132","lk0311","td0591","sl0531","uo0752","kq0351","tu0911","kp0701","ga0662","tx0062","jy0232","jo0031","fa0501","ak0272","ld0231","ep0511","yt0742","ul0781","ut0402","qf0222","ou0022","ji0861","td0781","ec0811","xj0121","sa0591","aw0751","ze0221","zo0262","gc0041","ml0131","lo0112","jx0171","mm0521","po0821","tx0522","up0301","ew0271","em0501","sa0431","xj0851","yt0141","mq0322","fu0661","uu0571","td0063","fj0482","wo0851","ti0662","ff0582","mi0621","fpgb","kl0811","ld0801","st0251","eu0931","wa0871","tj0581","ax0201","id0821","kp0102","lq0562","pp0741","jz0382","ef0541","ew0611","so0511","qc0742","af0811","ul0491","gk0571","fl0561","xw0761","xm0461","kj0571","pz0611","zz0603","jg0992","zj0101","of0161","ed0311","fj0472","uq0283","po0411","xx0531","uu0141"]},{"t_end":"2026-02-26T16:42:00+00:00","cumulative_submissions":3417,"cumulative_students":90,"mean_incorrectness":0.481,"struggle_buckets":[{"label":"On Track","count":0},{"label":"Minor Issues","count":1},{"label":"Struggling","count":2},{"label":"Needs Help","count":87}],"difficulty_buckets":[{"label":"Easy","count":1},{"label":"Medium","count":3},{"label":"Hard","count":28},{"label":"Very Hard","count":0}],"needs_help_ids":["jo0841","qf0132","lk0311","sl0531","uo0752","td0591","kq0351","tu0911","kp0701","ga0662","tx0062","jy0232","jo0031","fa0501","ld0231","ak0272","yt0742","ep0511","ut0402","ul0781","qf0222","ou0022","td0781","ji0861","ec0811","xj0121","sa0591","zz0603","aw0751","ze0221","zo0262","gc0041","ml0131","jx0171","mm0521","lo0112","po0821","id0821","tx0522","up0301","ew0271","sa0431","em0501","yt0141","mq0322","xj0851","fu0661","uu0571","fj0482","wo0851","ti0662","fpgb","mi0621","ff0582","kl0811","td0063","ld0801","eu0931","tj0581","wa0871","st0251","kp0102","ax0201","pp0741","lq0562","jz0382","ef0541","so0511","ew0611","xw0761","fl0561","gk0571","qc0742","af0811","kj0571","ul0491","pz0611","xm0461","fj0472","jg0992","zj0101","ed0311","po0411","uq0283","of0161","xx0531","uu0141"]},{"t_end":"2026-02-26T16:48:00+00:00","cumulative_submissions":3488,"cumulative_students":90,"mean_incorrectness":0.48,"struggle_buckets":[{"label":"On Track","count":0},{"label":"Minor Issues","count":1},{"label":"Struggling","count":2},{"label":"Needs Help","count":87}],"difficulty_buckets":[{"label":"Easy","count":1},{"label":"Medium","count":2},{"label":"Hard","count":29},{"label":"Very Hard","count":0}],"needs_help_ids":["jo0841","qf0132","lk0311","sl0531","uo0752","td0591","zz0603","kq0351","tu0911","kp0701","ga0662","tx0062","jy0232","ld0231","fa0501","jo0031","ak0272","yt0742","ep0511","ut0402","ul0781","mq0322","ou0022","ec0811","qf0222","xj0121","td0781","ji0861","aw0751","sa0591","id0821","ze0221","gc0041","ml0131","zo0262","jx0171","lo0112","mm0521","po0821","tx0522","up0301","ew0271","em0501","sa0431","fu0661","yt0141","uu0571","xj0851","fj0482","wo0851","mi0621","ti0662","ff0582","fpgb","kl0811","ld0801","tj0581","eu0931","kp0102","wa0871","st0251","jz0382","ax0201","xx0531","lq0562","ef0541","pp0741","so0511","ew0611","qc0742","fl0561","gk0571","xw0761","kj0571","af0811","jg0992","pz0611","ul0491","fj0472","ed0311","po0411","uq0283","xm0461","of0161","zj0101","uu0141","td0063"]},{"t_end":"2026-02-26T16:54:00+00:00","cumulative_submissions":3544,"cumulative_students":90,"mean_incorrectness":0.481,"struggle_buckets":[{"label":"On Track","count":0},{"label":"Minor Issues","count":1},{"label":"Struggling","count":2},{"label":"Needs Help","count":87}],"difficulty_buckets":[{"label":"Easy","count":1},{"label":"Medium","count":2},{"label":"Hard","count":29},{"label":"Very Hard","count":0}],"needs_help_ids":["jo0841","qf0132","lk0311","sl0531","uo0752","td0591","zz0603","kq0351","tu0911","kp0701","ga0662","tx0062","jy0232","ld0231","fa0501","jo0031","ak0272","yt0742","fpgb","ep0511","ut0402","ul0781","mq0322","ou0022","ec0811","qf0222","xj0121","td0781","ji0861","id0821","aw0751","sa0591","ze0221","gc0041","ml0131","gk0571","zo0262","jx0171","lo0112","mm0521","po0821","tx0522","up0301","ew0271","em0501","sa0431","yt0141","fu0661","uu0571","xj0851","fj0482","wo0851","mi0621","ff0582","ti0662","kl0811","ld0801","kj0571","tj0581","eu0931","kp0102","wa0871","st0251","jz0382","xx0531","ax0201","lq0562","ef0541","pp0741","so0511","fl0561","xw0761","ew0611","qc0742","af0811","jg0992","pz0611","ul0491","of0161","fj0472","ed0311","po0411","uq0283","xm0461","zj0101","uu0141","td0063"]},{"t_end":"2026-02-26T17:00:00+00:00","cumulative_submissions":3557,"cumulative_students":90,"mean_incorrectness":0.481,"struggle_buckets":[{"label":"On Track","count":0},{"label":"Minor Issues","count":1},{"label":"Struggling","count":2},{"label":"Needs Help","count":87}],"difficulty_buckets":[{"label":"Easy","count":1},{"label":"Medium","count":2},{"label":"Hard","count":29},{"label":"Very Hard","count":0}],"needs_help_ids":["jo0841","qf0132","lk0311","sl0531","uo0752","td0591","zz0603","kq0351","tu0911","kp0701","ga0662","tx0062","jy0232","ld0231","fa0501","jo0031","ak0272","fpgb","yt0742","ep0511","ut0402","ul0781","mq0322","ou0022","ec0811","qf0222","xj0121","td0781","ji0861","id0821","aw0751","sa0591","ze0221","gc0041","ml0131","gk0571","zo0262","jx0171","lo0112","mm0521","po0821","tx0522","up0301","ew0271","em0501","sa0431","yt0141","fu0661","uu0571","xj0851","fj0482","wo0851","mi0621","ff0582","ti0662","kl0811","kj0571","ld0801","tj0581","eu0931","kp0102","fj0472","wa0871","st0251","jz0382","xx0531","ax0201","lq0562","ef0541","pp0741","so0511","fl0561","xw0761","ew0611","qc0742","af0811","jg0992","pz0611","ul0491","of0161","ed0311","po0411","uq0283","xm0461","zj0101","uu0141","td0063"]}]}