{"nodes": [{"id": "measurement", "label": "measurement.py", "file_type": "code", "source_file": "code2\\learning_dashboard\\models\\measurement.py", "source_location": "L1"}, {"id": "measurement_compute_incorrectness_with_confidence", "label": "compute_incorrectness_with_confidence()", "file_type": "code", "source_file": "code2\\learning_dashboard\\models\\measurement.py", "source_location": "L9"}, {"id": "measurement_rationale_1", "label": "Phase 1 \u2014 Measurement confidence for AI-derived incorrectness scores.", "file_type": "rationale", "source_file": "code2\\learning_dashboard\\models\\measurement.py", "source_location": "L1"}, {"id": "measurement_rationale_10", "label": "Wrap analytics.compute_incorrectness_column() and add confidence metadata.", "file_type": "rationale", "source_file": "code2\\learning_dashboard\\models\\measurement.py", "source_location": "L10"}], "edges": [{"source": "measurement", "target": "numpy", "relation": "imports", "confidence": "EXTRACTED", "source_file": "code2\\learning_dashboard\\models\\measurement.py", "source_location": "L3", "weight": 1.0}, {"source": "measurement", "target": "pandas", "relation": "imports", "confidence": "EXTRACTED", "source_file": "code2\\learning_dashboard\\models\\measurement.py", "source_location": "L4", "weight": 1.0}, {"source": "measurement", "target": "learning_dashboard", "relation": "imports_from", "confidence": "EXTRACTED", "source_file": "code2\\learning_dashboard\\models\\measurement.py", "source_location": "L6", "weight": 1.0}, {"source": "measurement", "target": "measurement_compute_incorrectness_with_confidence", "relation": "contains", "confidence": "EXTRACTED", "source_file": "code2\\learning_dashboard\\models\\measurement.py", "source_location": "L9", "weight": 1.0}, {"source": "measurement_rationale_1", "target": "measurement", "relation": "rationale_for", "confidence": "EXTRACTED", "source_file": "code2\\learning_dashboard\\models\\measurement.py", "source_location": "L1", "weight": 1.0}, {"source": "measurement_rationale_10", "target": "measurement_compute_incorrectness_with_confidence", "relation": "rationale_for", "confidence": "EXTRACTED", "source_file": "code2\\learning_dashboard\\models\\measurement.py", "source_location": "L10", "weight": 1.0}]}